swagger_generator/__init__.py
swagger_generator/__main__.py
swagger_generator/build.py
swagger_generator/config_folder.py
swagger_generator/data_type.py
swagger_generator/insert.py
swagger_generator/swagger_info.py
swagger_generator/template.py
swagger_generator/template_arg.py
swagger_generator/util.py
py_swagger_generator-1.1.0.dist-info/LICENSE
py_swagger_generator-1.1.0.dist-info/METADATA
py_swagger_generator-1.1.0.dist-info/WHEEL
py_swagger_generator-1.1.0.dist-info/entry_points.txt
py_swagger_generator-1.1.0.dist-info/top_level.txt
py_swagger_generator-1.1.0.dist-info/RECORD
