Metadata-Version: 2.1
Name: py-swagger-generator
Version: 1.1.0
Summary: A Package that can be used to create swagger yaml using templates
Home-page: https://github.com/RedstoneMedia/py_swagger_generator
Author: RedstoneMedia
License: GNU General Public License v3.0
Keywords: swagger generator templates tool
Platform: UNKNOWN
Requires-Dist: PyYAML (>=5.3.1)
